sel_ide_runner/__init__.py
sel_ide_runner/__main__.py
sel_ide_runner/case.py
sel_ide_runner/script.py
sel_ide_runner/selenium_emu.py
sel_ide_runner/step.py
sel_ide_runner/suite.py
sel_ide_runner/util.py
sel_ide_runner-1.0.0.dist-info/LICENSE
sel_ide_runner-1.0.0.dist-info/METADATA
sel_ide_runner-1.0.0.dist-info/WHEEL
sel_ide_runner-1.0.0.dist-info/entry_points.txt
sel_ide_runner-1.0.0.dist-info/top_level.txt
sel_ide_runner-1.0.0.dist-info/RECORD
