Metadata-Version: 2.1
Name: sel-ide-runner
Version: 1.0.0
Summary: Python Selenium IDE runner
Home-page: https://github.com/pe2mbs/pykeystore
Author: Marc Bertens-Nguyen
Author-email: Marc Berten-Nguyen <m.bertens@pe2mbs.nl>
Project-URL: Homepage, https://github.com/pe2mbs/sel_ide_runner
Project-URL: Bug Tracker, https://github.com/pe2mbs/sel_ide_runner/issues
Classifier: Programming Language :: Python :: 3
Classifier: Intended Audience :: Developers
Classifier: License :: OSI Approved :: GNU General Public License v2 (GPLv2)
Classifier: Operating System :: OS Independent
Classifier: Topic :: Security :: Cryptography
Requires-Python: >=3.8
License-File: LICENSE
Requires-Dist: PyYAML
Requires-Dist: robotframework-seleniumlibrary (==6.0.0)
Requires-Dist: pykeystore
